radiant/__init__.py
radiant/instrumentor.py
radiant_sdk-0.140.0.dist-info/METADATA
radiant_sdk-0.140.0.dist-info/WHEEL
radiant_sdk-0.140.0.dist-info/RECORD
